Metadata-Version: 2.1
Name: AkritiSehgal-101703048-Outlier-removal
Version: 0.1.3
Summary: A small example package for removal of outliers in the given dataset
Home-page: UNKNOWN
Author: Akriti Sehgal
Author-email: akritisehgal9@gmail.com
License: UNKNOWN
Download-URL: https://github.com/AkritiSehgal/outlier_removal_101703048/archive/v_01.3.tar.gz
Keywords: command-line,Outliers,outlier-removal,row-removal
Platform: UNKNOWN
Classifier: Programming Language :: Python :: 3
Classifier: License :: OSI Approved :: MIT License
Classifier: Operating System :: OS Independent
Requires-Python: >=3.6
